apereo/__init__.py
apereo/pipelines/__init__.py
apereo/pipelines/groups.py
apereo/pipelines/test_groups.py
apereosocialpipeline-0.0.4.dist-info/METADATA
apereosocialpipeline-0.0.4.dist-info/WHEEL
apereosocialpipeline-0.0.4.dist-info/top_level.txt
apereosocialpipeline-0.0.4.dist-info/RECORD
