Metadata-Version: 2.4
Name: ApereoSocialPipeline
Version: 0.0.4
Summary: Social Auth pipeline for use with OIDC SSO and Apereo CAS
Author-email: Simon Lyngshede <slyngshede@wikimedia.org>
License: ISC License
Project-URL: Homepage, https://gitlab.wikimedia.org/slyngshede/apereo_cas_social_pipeline
Project-URL: Repository, https://gitlab.wikimedia.org/slyngshede/apereo_cas_social_pipeline.git
Requires-Dist: django
